apache_flink-2.1.0.data/scripts/find-flink-home.sh
apache_flink-2.1.0.data/scripts/find_flink_home.py
apache_flink-2.1.0.data/scripts/pyflink-shell.sh
apache_flink-2.1.0.dist-info/licenses/LICENSE
pyflink/README.txt
pyflink/__init__.py
pyflink/find_flink_home.py
pyflink/gen_protos.py
pyflink/java_gateway.py
pyflink/pyflink_callback_server.py
pyflink/pyflink_gateway_server.py
pyflink/serializers.py
pyflink/shell.py
pyflink/version.py
pyflink/bin/bash-java-utils.sh
pyflink/bin/config-parser-utils.sh
pyflink/bin/config.sh
pyflink/bin/find-flink-home.sh
pyflink/bin/flink
pyflink/bin/flink-console.sh
pyflink/bin/flink-daemon.sh
pyflink/bin/historyserver.sh
pyflink/bin/jobmanager.sh
pyflink/bin/kubernetes-jobmanager.sh
pyflink/bin/kubernetes-session.sh
pyflink/bin/kubernetes-taskmanager.sh
pyflink/bin/migrate-config-file.sh
pyflink/bin/pyflink-shell.sh
pyflink/bin/pyflink-udf-runner.bat
pyflink/bin/pyflink-udf-runner.sh
pyflink/bin/sql-client.sh
pyflink/bin/sql-gateway.sh
pyflink/bin/standalone-job.sh
pyflink/bin/start-cluster.sh
pyflink/bin/start-zookeeper-quorum.sh
pyflink/bin/stop-cluster.sh
pyflink/bin/stop-zookeeper-quorum.sh
pyflink/bin/taskmanager.sh
pyflink/bin/yarn-session.sh
pyflink/bin/zookeeper.sh
pyflink/common/__init__.py
pyflink/common/completable_future.py
pyflink/common/config_options.py
pyflink/common/configuration.py
pyflink/common/constants.py
pyflink/common/execution_config.py
pyflink/common/input_dependency_constraint.py
pyflink/common/io.py
pyflink/common/job_client.py
pyflink/common/job_execution_result.py
pyflink/common/job_id.py
pyflink/common/job_status.py
pyflink/common/restart_strategy.py
pyflink/common/serialization.py
pyflink/common/serializer.py
pyflink/common/time.py
pyflink/common/typeinfo.py
pyflink/common/types.py
pyflink/common/utils.py
pyflink/common/watermark_strategy.py
pyflink/conf/config.yaml
pyflink/conf/log4j-cli.properties
pyflink/conf/log4j-console.properties
pyflink/conf/log4j-session.properties
pyflink/conf/log4j.properties
pyflink/conf/logback-console.xml
apache_flink-2.1.0.dist-info/METADATA
apache_flink-2.1.0.dist-info/WHEEL
apache_flink-2.1.0.dist-info/top_level.txt
apache_flink-2.1.0.dist-info/RECORD
